vulturenb/__init__.py
vulturenb/cli.py
vulturenb/notebook_converter.py
vulturenb/printer.py
vulturenb/vulture_runner.py
vulturenb-1.0.1.dist-info/licenses/LICENSE
vulturenb-1.0.1.dist-info/METADATA
vulturenb-1.0.1.dist-info/WHEEL
vulturenb-1.0.1.dist-info/entry_points.txt
vulturenb-1.0.1.dist-info/top_level.txt
vulturenb-1.0.1.dist-info/RECORD
