Metadata-Version: 2.4
Name: vulturenb
Version: 1.0.1
Summary: Wrapper around the vulture tool to include Jupyter notebooks.
Classifier: Programming Language :: Python :: 3
Classifier: License :: OSI Approved :: MIT License
Classifier: Operating System :: OS Independent
Requires-Python: >=3.10
License-File: LICENSE
Requires-Dist: vulture
Requires-Dist: nbconvert
Requires-Dist: loguru
Requires-Dist: rich
Requires-Dist: ipykernel
Provides-Extra: dev
Requires-Dist: ruff; extra == "dev"
Requires-Dist: build; extra == "dev"
Requires-Dist: twine; extra == "dev"
Dynamic: license-file
